terravide/__init__.py
terravide/src/GroundClassification.py
terravide/src/Preprocessing.py
terravide/src/__init__.py
terravide/src/dataset.py
terravide/src/info.py
TerraVide-0.1.6.dist-info/LICENSE.txt
TerraVide-0.1.6.dist-info/METADATA
TerraVide-0.1.6.dist-info/WHEEL
TerraVide-0.1.6.dist-info/top_level.txt
TerraVide-0.1.6.dist-info/RECORD
